echonextdi/__init__.py
echonextdi/containers/container.py
echonextdi/containers/declarative_container.py
echonextdi/containers/dynamic_container.py
echonextdi/depends.py
echonextdi/exceptions.py
echonextdi/providers/callable_provider.py
echonextdi/providers/configuration_provider.py
echonextdi/providers/dict_provider.py
echonextdi/providers/factory_provider.py
echonextdi/providers/list_provider.py
echonextdi/providers/object_provider.py
echonextdi/providers/provider.py
echonextdi/providers/resource_provider.py
echonextdi/providers/singleton_provider.py
echonextdi-0.2.0.dist-info/LICENSE
echonextdi-0.2.0.dist-info/METADATA
echonextdi-0.2.0.dist-info/WHEEL
echonextdi-0.2.0.dist-info/RECORD
