Metadata-Version: 2.1
Name: echonextdi
Version: 0.2.0
Summary: Light and intuitive Dependency Injection Library for pyEchoNext Project
License: GNU LGPL 2.1
Author: alexeev-prog
Author-email: alexeev.dev@mail.ru
Requires-Python: >=3.9,<4.0
Classifier: License :: Other/Proprietary License
Classifier: Programming Language :: Python :: 3
Classifier: Programming Language :: Python :: 3.9
Classifier: Programming Language :: Python :: 3.10
Classifier: Programming Language :: Python :: 3.11
Classifier: Programming Language :: Python :: 3.12
Classifier: Programming Language :: Python :: 3.13
Requires-Dist: orjson (>=3.10,<4.0)
Requires-Dist: pyyaml (>=6.0,<7.0)
Requires-Dist: toml (>=0.10,<0.11)
